{
  "reply_mode": 1,
  "time_before_overtime": 0,
  "set_priority_automatically": false,
  "is_follow": 0,
  "category_2": "",
  "category_1": "1782786995587105",
  "follower_avatar": "https://s16-imfile-sg.feishucdn.com/static-resource/v1/v2_adbdd8f4-12fb-4d14-bcf3-833a7a164fhu~?image_size=72x72&cut_type=&quality=&format=png&sticker_format=.webp",
  "follower": "Itay Filiba",
  "create_time": 1708079893,
  "deadline": 0,
  "archive_board_id": 1705151646989732,
  "replies": [
    {
      "is_hide_reply": false,
      "create_time": 1708085404,
      "auto_close_hit": 0,
      "id": 7336169956637213000,
      "reply_role": null,
      "staff_id": "",
      "type": 0,
      "is_questioner": false,
      "reply_to_user_role": null,
      "is_update": false,
      "reply_to_user_name": "Jaafar Alla",
      "editable": 0,
      "reply_email": "itay.filiba@tiktok.com",
      "is_blocked_role": false,
      "is_final_solution": 1,
      "reply_name": "Itay Filiba",
      "reply_to_user_id": 6847081183651775000,
      "is_hide_name": false,
      "core_user_id": "7187710198676145154",
      "name": "Itay Filiba",
      "blocked_roles": [],
      "items": [
        {
          "content": "<p>Hi Jaffar,&nbsp;<br><br></p><p>Thank you for your questions. I will be happy to provide information of this.&nbsp;</p><ul><li>TikTok LIVE Studio is desktop streaming software created by TikTok. It is used to stream to TikTok using this professional software instead of using the mobile device camera. </li><li>Recently they launched a cool feature called &#39;compatibility mode&#39; that allows streaming to TikTok both 16:9 and 9:16 feeds at the same time. The end user can switch between the vertical and horizontal feed. End users on desktop will see the horizontal feed.</li><li>This new feature is still not 100% stable as it&#39;s still on beta. Clients should be aware of this.&nbsp;&nbsp;</li><li>TikTok launched this cool feature for gamers who stream gaming content on TikTok. </li><li>Other clients, that do not stream gaming content, can still use Live Studio, but they might experience their live steam to be not recommended on the ForYou Page. Means less exposure&nbsp;<span style=\"color: #FF7528;\"><strong>(this is internal information, do not share this externally)</strong></span><strong>.&nbsp;</strong></li></ul><p><br></p><p>My recommendation&nbsp;</p><ol><li>Get your client LIVE STUDIO access for both their main account and test account and let them test this feature.&nbsp;</li><li>If they wish to use this on their live stream, they should have a backup plan to switch to OBS LIVE (streaming with another streaming software). Therefore, you should apply for OBS LIVE access for your clients as well (both main and test account).&nbsp;</li><li>Clients should be aware there is a change this might effect their exposure since it&#39;s a new feature. Do not provide additional info on that.&nbsp;&nbsp;</li></ol><p><br></p><p>Hope this info is useful. If you have further questions related this matter, please feel free to re-open this ticket and ask.&nbsp;</p><p><br></p><p>Best regards,&nbsp;</p><p>Itay&nbsp;</p>",
          "type": 6
        }
      ],
      "avatar": "https://s16-imfile-sg.feishucdn.com/static-resource/v1/v2_adbdd8f4-12fb-4d14-bcf3-833a7a164fhu~?image_size=640x640&cut_type=&quality=&format=png&sticker_format=.webp",
      "context": {}
    },
    {
      "is_hide_reply": false,
      "create_time": 1708088998,
      "auto_close_hit": 0,
      "id": 7336186085544133000,
      "reply_role": null,
      "staff_id": "",
      "type": 1,
      "is_questioner": true,
      "is_update": false,
      "editable": 0,
      "reply_email": "",
      "is_blocked_role": false,
      "is_final_solution": 0,
      "reply_name": "Jaafar Alla",
      "reply_to_user_id": null,
      "is_hide_name": false,
      "core_user_id": "6847081183651775494",
      "name": "Jaafar Alla",
      "blocked_roles": [],
      "items": [
        {
          "content": "<p>Hello Itay, thanks for these info. So we cannot inform the client about the non exposure on for you page?&nbsp;</p><p>Also, I can&#39;t seem to have the access to request Live Studio from my end, how can we proceed? Can you please confirm for how many days the access will be available ?</p><p>The client is also asking if there is an impact on the live boost, here is the client question below:</p><p>&#34;Please confirm once you know whether it&#39;s possible to have both 9x16 and 16x9, for the user to select their viewing preference.</p><p>Would this be linked to one stream link to also be boosted in tandem?&#34;</p>",
          "type": 6
        }
      ],
      "avatar": "https://s16-imfile-sg.feishucdn.com/static-resource/v1/v3_007d_1bdc9be1-3d26-4c82-86f6-b1af83a1aahu~?image_size=640x640&cut_type=&quality=&format=png&sticker_format=.webp",
      "context": {}
    },
    {
      "is_hide_reply": false,
      "create_time": 1708090166,
      "auto_close_hit": 0,
      "id": 7336190692265394000,
      "reply_role": null,
      "staff_id": "",
      "type": 0,
      "is_questioner": false,
      "reply_to_user_role": null,
      "is_update": false,
      "reply_to_user_name": "Jaafar Alla",
      "editable": 0,
      "reply_email": "itay.filiba@tiktok.com",
      "is_blocked_role": false,
      "is_final_solution": 1,
      "reply_name": "Itay Filiba",
      "reply_to_user_id": 6847081183651775000,
      "is_hide_name": false,
      "core_user_id": "7187710198676145154",
      "name": "Itay Filiba",
      "blocked_roles": [],
      "items": [
        {
          "content": "<p>Hi Jaffar,&nbsp;</p><p><br></p><p><span style=\"color: #333333;\"><strong>So we cannot inform the client about the non exposure on for you page?&nbsp;</strong></span></p><p><span style=\"color: #333333;\">You can tell the client that using this feature might effect their organic performance since this is a new feature.</span><br><br></p><p><span style=\"color: #333333;\"><strong>Also, I can&#39;t seem to have the access to request Live Studio from my end, how can we proceed?</strong></span></p><p><span style=\"color: #333333;\">Request LIVE Studio M10N access. Video guide <a target=\"_blank\" href=\"https://vcp.to/vobsaccess\">here</a></span><br></p><p><br></p><p><span style=\"color: #333333;\"><strong>Can you please confirm for how many days the access will be available?</strong></span></p><p><span style=\"color: #333333;\">14 days</span></p><p><br></p><p><span style=\"color: #333333;\"><strong>&#34;Please confirm once you know whether it&#39;s possible to have both 9x16 and 16x9, for the user to select their viewing preference.</strong></span></p><p><span style=\"color: #333333;\"><strong>Would this be linked to one stream link to also be boosted in tandem?&#34;</strong></span></p><p>Yes. On Live Studio they don&#39;t need to use Stream Key as they do on OBS LIVE access. Encourage them to test this feature on test account. Give them access to LIVE Studio.&nbsp;</p><p><br></p><p>Hope this is helpful</p><p><br></p><p>Best,&nbsp;</p><p>Itay</p>",
          "type": 6
        }
      ],
      "avatar": "https://s16-imfile-sg.feishucdn.com/static-resource/v1/v2_adbdd8f4-12fb-4d14-bcf3-833a7a164fhu~?image_size=640x640&cut_type=&quality=&format=png&sticker_format=.webp",
      "context": {}
    }
  ],
  "enable_forced_order_type": 0,
  "plat_id": 1736490999244882,
  "archive_category_2_name": "",
  "pending_from_follower": false,
  "id": 1880154,
  "workflow_nodes": [],
  "board_id": 1705151646989732,
  "employee_email": "itay.filiba@bytedance.com",
  "is_support_suggestion": 0,
  "title": "Balenciaga Show March 2024",
  "category_1_name": "Livestream - Ask a Question",
  "auto_close_hit": 0,
  "relation_qual": [],
  "accountpass": 0,
  "priority": 2,
  "inner": 1,
  "vip_types": [],
  "is_impending_overtime": 0,
  "creater_lark_avatar": "https://s16-imfile-sg.feishucdn.com/static-resource/v1/v3_007d_1bdc9be1-3d26-4c82-86f6-b1af83a1aahu~?image_size=72x72&cut_type=&quality=&format=png&sticker_format=.webp",
  "enable_compliance_mode": false,
  "type": 0,
  "current_role": null,
  "fd_permission": 1,
  "status": 3,
  "business_data": [],
  "update_time": 1708351227,
  "owner_name": "Jaafar Alla",
  "enable_auto_close_v2": 0,
  "time_after_overtime": 0,
  "swim_lane_status": 5,
  "enable_forced_order_tag": 1,
  "satisfied": 0,
  "category_2_name": "",
  "reply_name": " MPO Technical Implementation  Team",
  "is_guest": false,
  "archive_category_2": "",
  "archive_category_1_name": "Livestream - Ask a Question",
  "archive_category_1": "1782786995587105",
  "allow_reopen": 0,
  "categories": [
    {
      "to_user": 1,
      "categories_id": "1754600019392513",
      "cate_1_form_id": 1754543111783458,
      "sub_cates": [],
      "value": "Livestream Consultation"
    },
    {
      "to_user": 1,
      "categories_id": "1782786995587105",
      "cate_1_form_id": 1782788250818562,
      "sub_cates": [],
      "value": "Livestream - Ask a Question"
    }
  ],
  "core_user_id": "6847081183651775494",
  "plat_name": "MPO Technical Implementation",
  "follower_role": "admin",
  "remark": "",
  "show_auto_assign": false,
  "is_overtime": 0,
  "creater_lark_name": "Jaafar Alla",
  "follow_employee_id": 8282921,
  "is_order_top": 0,
  "urged": 0,
  "im_chat_id": "",
  "is_delay": 0,
  "enable_forced_priority": 0,
  "pending_time": 2422806,
  "debug_permission": 1,
  "is_vip": 0,
  "items": [
    {
      "label": "<p spellcheck=\"true\">MPO LIVE helps advertisers go live on TikTok. Use this form to submit a general question to the MPO LIVE team regarding live streaming on TikTok. This form is not for troubleshooting and bugs. For troubleshooting and bugs please use: Athena &gt; TikTok Internal Tickets &gt; Branding solutions &gt; Livestream Traffic Solutions. ///Link to Athena Internal Tickets: https://vcp.to/atint</p>",
      "content": "",
      "valid": true,
      "item_id": 1782788572065825,
      "type": 12,
      "option_meaning": -1
    },
    {
      "label": "Question title",
      "content": "Balenciaga Show March 2024",
      "valid": true,
      "item_id": 1782788250818578,
      "type": 14,
      "option_meaning": -1
    },
    {
      "label": "Region",
      "content": "EU-FR",
      "valid": true,
      "key": "EU",
      "item_id": 1782788281423874,
      "type": 4,
      "option_meaning": 0
    },
    {
      "label": "Client Name",
      "content": "Balenciaga",
      "valid": true,
      "item_id": 1782788281425938,
      "type": 1,
      "option_meaning": -1
    },
    {
      "label": "Advertiser ID",
      "content": "",
      "valid": true,
      "item_id": 1782788344073218,
      "type": 18,
      "option_meaning": -1
    },
    {
      "label": "Ad Account ID",
      "content": [
        "6881650673079812098"
      ],
      "valid": true,
      "item_id": 1782788344073234,
      "type": 18,
      "option_meaning": -1
    },
    {
      "label": "UID of the TikTok account",
      "content": "",
      "valid": true,
      "item_id": 1782788344073250,
      "type": 18,
      "option_meaning": -1
    },
    {
      "label": "Handle of the TikTok account",
      "content": [
        "balenciaga"
      ],
      "valid": true,
      "item_id": 1782788344073266,
      "type": 18,
      "option_meaning": -1
    },
    {
      "label": "Question text",
      "content": "The client is asking if they can have the horizontal feature for their livestream in 2 weeks. Please see the feature attached",
      "valid": true,
      "item_id": 1782788344074242,
      "type": 2,
      "option_meaning": -1
    },
    {
      "label": "File or screenshot",
      "content": [
        {
          "file_type": "png",
          "file_name": "Bal_TT_Studio.png",
          "file_url": "https://p16-athena-sign-sg.ibyteimg.com/tos-alisg-i-6g3pebcbys-sg/d4e3b1f516074d7fb6488c361afddafd.png~tplv-6g3pebcbys-image.jpeg?lk3s=cbe26b3a&x-expires=4832838033&x-signature=aN5Zye4tUhKD9kGaL65o8hBQMU8%3D",
          "file_key": "tos-alisg-i-6g3pebcbys-sg/d4e3b1f516074d7fb6488c361afddafd.png",
          "url": "https://p16-athena-sign-sg.ibyteimg.com/tos-alisg-i-6g3pebcbys-sg/d4e3b1f516074d7fb6488c361afddafd.png~tplv-6g3pebcbys-image.jpeg?lk3s=cbe26b3a&x-expires=4832838033&x-signature=aN5Zye4tUhKD9kGaL65o8hBQMU8%3D",
          "size": 1965920
        },
        {
          "file_type": "png",
          "file_name": "Bal_TT.png",
          "file_url": "https://p16-athena-sign-sg.ibyteimg.com/tos-alisg-i-6g3pebcbys-sg/a079c9bcb07c47019c88e80e10904051.png~tplv-6g3pebcbys-image.jpeg?lk3s=cbe26b3a&x-expires=4832838033&x-signature=XZO2pMOGU4jBeT4Jwxy0iWXK7K4%3D",
          "file_key": "tos-alisg-i-6g3pebcbys-sg/a079c9bcb07c47019c88e80e10904051.png",
          "url": "https://p16-athena-sign-sg.ibyteimg.com/tos-alisg-i-6g3pebcbys-sg/a079c9bcb07c47019c88e80e10904051.png~tplv-6g3pebcbys-image.jpeg?lk3s=cbe26b3a&x-expires=4832838033&x-signature=XZO2pMOGU4jBeT4Jwxy0iWXK7K4%3D",
          "size": 1188855
        }
      ],
      "valid": true,
      "item_id": 1782788344074258,
      "type": 5,
      "option_meaning": -1
    },
    {
      "label": "categorization",
      "content": {
        "category_1_name": "Tiktok Livestream Consultation-Livestream - Ask a Question"
      },
      "valid": true,
      "item_id": 0,
      "type": 3,
      "option_meaning": -1
    }
  ],
  "fs_permission": 1,
  "auto_close_time_left": null
}